{"streams": [{"title": "\u6211\u66fe\u7ecf\u8de8\u8fc7\u5c71\u548c\u5927\u6d77", "link": "/2009", "id": "5161", "img": "http://dlpic.cdn.zhanqi.tv/live/20150401/5161_Z4Coi_2015-04-01-19-13-56.jpg", "anchor": "\u4f0d\u58f0 2009"}, {"title": "LGD_Yao \u611a\u4eba\u8282\u5feb\u4e50~", "link": "/lgd_yao", "id": "19183", "img": "http://dlpic.cdn.zhanqi.tv/live/20150401/19183_m3vFi_2015-04-01-19-14-37.jpg", "anchor": "lgd_yao"}, {"title": "\u8fd9\u662f\u4e00\u4e2a\u95fb\u8005\u4f24\u5fc3\u89c1\u8005\u6d41\u6cea\u7684\u76f4\u64ad\u95f4", "link": "/laoshusjq", "id": "2021", "img": "http://dlpic.cdn.zhanqi.tv/live/20150401/2021_0PzvF_2015-04-01-19-11-54.jpg", "anchor": "sjq\u8001\u9f20"}, {"title": "\u770b\u770bOB\u6d77\u9c9c\u56e2\u6bd4\u8d5b\u3002", "link": "/swjie", "id": "16501", "img": "http://dlpic.cdn.zhanqi.tv/live/20150401/16501_ng37g_2015-04-01-19-12-32.jpg", "anchor": "\u4e09\u6708\u3002"}, {"title": "\u6e38\u620f\u98ce\u4e91\u4e00\u5957", "link": "/11158", "id": "83", "img": "http://dlpic.cdn.zhanqi.tv/live/20150401/83_dotati4001_2015-04-01-19-11-26.jpg", "anchor": "\u6e38\u620f\u98ce\u4e91\u4e00\u5957 24H"}, {"title": "BGM DOTA2 GAME TIME", "link": "/origx", "id": "6625", "img": "http://dlpic.cdn.zhanqi.tv/live/20150401/6625_a9e8j_2015-04-01-19-12-07.jpg", "anchor": "___1"}, {"title": "\u2766AZWBP.5 \u4eca\u5929\u6211\u80fd\u674010\u4e2a", "link": "/azwbp5", "id": "6729", "img": "http://dlpic.cdn.zhanqi.tv/live/20150401/6729_Pwx4h_2015-04-01-19-14-10.jpg", "anchor": "\u624b\u98ce\u884c\u72c2\u9b54"}, {"title": "\u5fd7\u795e\u6559\u4f60\u6253Dota", "link": "/1127410", "id": "21934", "img": "http://dlpic.cdn.zhanqi.tv/live/20150401/21934_kG8Pv_2015-04-01-19-11-44.jpg", "anchor": "\u5076\u4e86\u4e2a\u64e6"}, {"title": "\u6355\u9c7c~\u6355\u9c7c\uff01", "link": "/mrzz", "id": "11816", "img": "http://dlpic.cdn.zhanqi.tv/live/20150401/11816_bDWLO_2015-04-01-19-13-44_2.jpg", "anchor": "biu\u2022biu.biu_MkehP"}, {"title": "\u64ad\u64ad\u64ad\u5575\u5575\u5575", "link": "/1142425", "id": "36950", "img": "http://dlpic.cdn.zhanqi.tv/live/20150401/36950_Yoyyo_2015-04-01-19-13-01.jpg", "anchor": "Vevinassssss"}, {"title": "\u65b0\u624b\u5a31\u4e50\u5411\u778e\u64ad\u3002", "link": "/gogo666", "id": "36889", "img": "http://dlpic.cdn.zhanqi.tv/live/20150401/36889_sZvhQ_2015-04-01-19-13-29.jpg", "anchor": "\u5c0f\u5e15\u5409"}, {"title": "\u2464\u591c\u7b19\u6b4c\u4e1c\u5357\u4e9a\u6293\u9c7c", "link": "/1135971", "id": "30496", "img": "http://dlpic.cdn.zhanqi.tv/live/20150401/30496_qQiRg_2015-04-01-19-13-42.jpg", "anchor": "\u620a\u591c\u7b19\u6b4c"}, {"title": "\u7ca4\u8bed\u9891\u9053\u3002\u4f5b\u5c71\u5605\u7c73\u4e00\u9f50\u9ece\u73a9\u54af", "link": "/1133499", "id": "28024", "img": "http://dlpic.cdn.zhanqi.tv/live/20150401/28024_aGuly_2015-04-01-19-13-21.jpg", "anchor": "\u5927\u6728\u8001\u5e08~"}, {"title": "\u6211\u89c9\u5f97\u6211\u7684\u6c34\u5e73\u8fd8\u53ef\u4ee5\u5427\u3002", "link": "/qiaoge123", "id": "10936", "img": "http://dlpic.cdn.zhanqi.tv/live/20150401/10936_V42rE_2015-04-01-19-10-55.jpg", "anchor": "\u4e54\u54e5"}, {"title": "\u56db\u54e5\u6765\u80cc\u9505\uff084000\u6765\u5e72\uff09\u6765\u8ba2\u9605~", "link": "/1140384", "id": "34909", "img": "http://dlpic.cdn.zhanqi.tv/live/20150401/34909_fZf8h_2015-04-01-04-07-12.jpg", "anchor": "\u56db\u54e5\u6765\u80cc\u9505"}, {"title": "\u53ea\u898150\uff0c\u5c31\u80fd\u6ee1\u8db3~~", "link": "/sqfree", "id": "33614", "img": "http://dlpic.cdn.zhanqi.tv/live/20150401/33614_rtuo5_2015-04-01-19-12-00.jpg", "anchor": "SQfree!"}, {"title": "\u73a9\u561b \u522b\u8ba1\u8f83\u592a\u591a \u53ef\u80fd\u4f60\u4f1a\u66f4\u5feb\u4e50", "link": "/xiaodiao", "id": "21327", "img": "http://dlpic.cdn.zhanqi.tv/live/20150401/21327_hetQP_2015-04-01-19-09-33_2.jpg", "anchor": "\u5c0f\u5201"}, {"title": "BurNIng)\u996d\u524d\u8d5b\u540e\u5575\u4e00\u4e2a", "link": "/burning", "id": "2140", "img": "http://dlpic.cdn.zhanqi.tv/live/20150331/2140_LKgPG_2015-03-31-00-09-43.jpg", "anchor": "Burning"}, {"title": "Air \u5929\u68af\u7b2c\u4e00\u89c6\u89d2", "link": "/Air", "id": "784", "img": "http://dlpic.cdn.zhanqi.tv/live/20150331/784_d67cL_2015-03-31-23-35-50.jpg", "anchor": "Air."}, {"title": "\u6211\u5c31\u662fTI2EHOME\u7684\u5b8c\u7f8e\u732b~", "link": "/1138700", "id": "33225", "img": "http://dlpic.cdn.zhanqi.tv/live/20150401/33225_YAVpO_2015-04-01-19-08-09.jpg", "anchor": "\u5b8c\u7f8e\u732b~"}, {"title": "\u7537\u4eba\u5c31\u8981\u5bf9\u81ea\u5df1\u72e0\u4e00\u70b9\uff01\u8f931\u76d815\u4e2a\u4fef\u5367\u6491", "link": "/Ksssssss", "id": "407", "img": "http://dlpic.cdn.zhanqi.tv/live/20150401/407_kIJt1_2015-04-01-17-42-58.jpg", "anchor": "Ksssssss\u9648\u5f6c"}, {"title": "\u8001\u677f\uff0c\u676550\u5206\uff01", "link": "/naigege", "id": "737", "img": "http://dlpic.cdn.zhanqi.tv/live/20150331/737_CGq78_2015-03-31-16-50-22.jpg", "anchor": "DD  "}, {"title": "\u4eca\u665a\u8bad\u7ec3\uff0c\u8bad\u7ec3\u4e0d\u5f00\u76f4\u64ad\uff01", "link": "/eh820", "id": "161", "img": "http://dlpic.cdn.zhanqi.tv/live/20150401/ulTD75mZZ6_2015-04-01-00-56-25.jpg", "anchor": "820\u90b9\u501a\u5929"}, {"title": "Newbee_Rabbit \u5355\u6392\u5355\u6392", "link": "/13115", "id": "2044", "img": "http://dlpic.cdn.zhanqi.tv/live/20150401/2044_TZC9a_2015-04-01-13-13-57.jpg", "anchor": "\u738b\u7ae0"}, {"title": "SanSheng\u76f4\u64ad\u95f4.", "link": "/11468", "id": "393", "img": "http://dlpic.cdn.zhanqi.tv/live/20150331/393_1wM2x_2015-03-31-02-23-55.jpg", "anchor": "Newbee_SanSheng"}, {"title": "\u6211\u53ebMMY!!         \u3000\u3000\u3000", "link": "/mmy666", "id": "2133", "img": "http://dlpic.cdn.zhanqi.tv/live/20150323/2133_F0LBr_2015-03-23-01-21-26.jpg", "anchor": "lgd_mmy"}, {"title": "\u9c7c\u4eba\u8282\u5c31\u662f\u8981\u9c7c\uff01\u2764\u871c\u6843\u2764\u4e3b\u64ad\u83dc\u7684\u62a0\u811a\uff01", "link": "/mitao", "id": "8293", "img": "http://dlpic.cdn.zhanqi.tv/live/20150401/8293_IW0hj_2015-04-01-18-41-44.jpg", "anchor": "Cinderella\u871c\u6843"}, {"title": "\u51b2\u5206\u51b2\u5206\uff01\uff01\uff01\uff01GOGOGO", "link": "/11464", "id": "389", "img": "http://dlpic.cdn.zhanqi.tv/live/20150314/389_IrVnU_2015-03-14-20-52-20.jpg", "anchor": "Newbee_Hao"}, {"title": "\u5dc5\u5cf0\u8054\u8d5b\u7b2c\u4e09\u8d5b\u5b63 \u548c\u5c0f\u65b0\u4e00\u8d77\u770b\u6bd4\u8d5b\u5427", "link": "/xiaoxinangel", "id": "29695", "img": "http://dlpic.cdn.zhanqi.tv/live/20150401/29695_OWRLV_2015-04-01-17-21-27_2.jpg", "anchor": "\u5c0f\u65b0angel"}, {"title": " \u5c0fB\u65e5\u5e38\u722c\u68af \u5b66\u4e0d\u5230\u4e1c\u897f\u4f60\u780d\u6211", "link": "/Bokey22", "id": "248", "img": "http://dlpic.cdn.zhanqi.tv/live/20150401/SwemcfcVhJ_2015-04-01-17-08-52.jpg", "anchor": "Bokey"}]}